odoo/addons/account_invoice_export/README.rst
odoo/addons/account_invoice_export/__init__.py
odoo/addons/account_invoice_export/__manifest__.py
odoo/addons/account_invoice_export/data/mail_activity_type.xml
odoo/addons/account_invoice_export/i18n/account_invoice_export.pot
odoo/addons/account_invoice_export/i18n/it.po
odoo/addons/account_invoice_export/models/__init__.py
odoo/addons/account_invoice_export/models/account_move.py
odoo/addons/account_invoice_export/models/transmit_method.py
odoo/addons/account_invoice_export/readme/CONTRIBUTORS.md
odoo/addons/account_invoice_export/readme/CREDITS.md
odoo/addons/account_invoice_export/readme/DESCRIPTION.md
odoo/addons/account_invoice_export/static/description/icon.png
odoo/addons/account_invoice_export/static/description/index.html
odoo/addons/account_invoice_export/tests/__init__.py
odoo/addons/account_invoice_export/tests/common.py
odoo/addons/account_invoice_export/tests/test_export_invoice.py
odoo/addons/account_invoice_export/views/account_move.xml
odoo/addons/account_invoice_export/views/message_template.xml
odoo/addons/account_invoice_export/views/transmit_method.xml
odoo_addon_account_invoice_export-18.0.1.0.0.2.dist-info/METADATA
odoo_addon_account_invoice_export-18.0.1.0.0.2.dist-info/WHEEL
odoo_addon_account_invoice_export-18.0.1.0.0.2.dist-info/top_level.txt
odoo_addon_account_invoice_export-18.0.1.0.0.2.dist-info/RECORD
